odoo/addons/base_export_manager/README.rst
odoo/addons/base_export_manager/__init__.py
odoo/addons/base_export_manager/__manifest__.py
odoo/addons/base_export_manager/hooks.py
odoo/addons/base_export_manager/i18n/ar.po
odoo/addons/base_export_manager/i18n/base_export_manager.pot
odoo/addons/base_export_manager/i18n/bg.po
odoo/addons/base_export_manager/i18n/bs.po
odoo/addons/base_export_manager/i18n/ca.po
odoo/addons/base_export_manager/i18n/cs.po
odoo/addons/base_export_manager/i18n/da.po
odoo/addons/base_export_manager/i18n/de.po
odoo/addons/base_export_manager/i18n/el_GR.po
odoo/addons/base_export_manager/i18n/en_GB.po
odoo/addons/base_export_manager/i18n/es.po
odoo/addons/base_export_manager/i18n/es_AR.po
odoo/addons/base_export_manager/i18n/es_CL.po
odoo/addons/base_export_manager/i18n/es_CO.po
odoo/addons/base_export_manager/i18n/es_CR.po
odoo/addons/base_export_manager/i18n/es_DO.po
odoo/addons/base_export_manager/i18n/es_EC.po
odoo/addons/base_export_manager/i18n/es_ES.po
odoo/addons/base_export_manager/i18n/es_MX.po
odoo/addons/base_export_manager/i18n/es_PE.po
odoo/addons/base_export_manager/i18n/es_PY.po
odoo/addons/base_export_manager/i18n/es_VE.po
odoo/addons/base_export_manager/i18n/et.po
odoo/addons/base_export_manager/i18n/eu.po
odoo/addons/base_export_manager/i18n/fa.po
odoo/addons/base_export_manager/i18n/fi.po
odoo/addons/base_export_manager/i18n/fr.po
odoo/addons/base_export_manager/i18n/fr_CA.po
odoo/addons/base_export_manager/i18n/fr_CH.po
odoo/addons/base_export_manager/i18n/fr_FR.po
odoo/addons/base_export_manager/i18n/gl.po
odoo/addons/base_export_manager/i18n/he.po
odoo/addons/base_export_manager/i18n/hr.po
odoo/addons/base_export_manager/i18n/hr_HR.po
odoo/addons/base_export_manager/i18n/hu.po
odoo/addons/base_export_manager/i18n/id.po
odoo/addons/base_export_manager/i18n/it.po
odoo/addons/base_export_manager/i18n/ja.po
odoo/addons/base_export_manager/i18n/ko.po
odoo/addons/base_export_manager/i18n/lt.po
odoo11_addon_base_export_manager-11.0.1.0.0.99.dev6.dist-info/METADATA
odoo11_addon_base_export_manager-11.0.1.0.0.99.dev6.dist-info/WHEEL
odoo11_addon_base_export_manager-11.0.1.0.0.99.dev6.dist-info/top_level.txt
odoo11_addon_base_export_manager-11.0.1.0.0.99.dev6.dist-info/RECORD
